<?xml version="1.0" encoding="utf-8"?>
<Library xmlns="http://xml.form.manager.bg" xmlns:xsi="http://www.w3.org/2001/XMLSchema-instance">
  <Contracts xmlns="http://xml.form.manager.bg">
    <contract contractName="1/14/2015 12:46:30 AM">
      <contractNumber>1</contractNumber>
      <contractDate>1</contractDate>
      <contractDate2>1</contractDate2>
      <community>1</community>
      <contractEmployer>1</contractEmployer>
      <contractAddress>1</contractAddress>
      <agencyNumber>1</agencyNumber>
      <contractEmployee>1</contractEmployee>
      <employeeCity>1</employeeCity>
      <employeeIDN>1</employeeIDN>
      <identityCardNumber>1</identityCardNumber>
      <identityCardCreateDate>1</identityCardCreateDate>
      <firstSpecialty>1</firstSpecialty>
      <firstDiplomaNumber>1</firstDiplomaNumber>
      <firstDiplomaDate>1</firstDiplomaDate>
      <firstDiplomaCreator>1</firstDiplomaCreator>
      <secondSpecialty>1</secondSpecialty>
      <secondDiplomaNumber>1</secondDiplomaNumber>
      <secondDiplomaDate>1</secondDiplomaDate>
      <secondDiplomaCreator>1</secondDiplomaCreator>
      <workExperienceYears>1</workExperienceYears>
      <workExperienceMonths>11</workExperienceMonths>
      <workExperienceDays>1</workExperienceDays>
      <workExperienceYearsWords>1</workExperienceYearsWords>
      <workExperienceMonthsWords>1</workExperienceMonthsWords>
      <workExperienceDaysWords>1</workExperienceDaysWords>
      <workPosition>1</workPosition>
      <positionCode>1</positionCode>
      <workPlace>1</workPlace>
      <workTime>1</workTime>
      <testTerm>1</testTerm>
      <payment>1</payment>
      <paymentWords>1</paymentWords>
      <dateStartJob>1</dateStartJob>
    </contract>
  </Contracts>
</Library>